ladybug_blender/__init__.py
ladybug_blender-0.1.1.dist-info/LICENSE
ladybug_blender-0.1.1.dist-info/METADATA
ladybug_blender-0.1.1.dist-info/WHEEL
ladybug_blender-0.1.1.dist-info/top_level.txt
ladybug_blender-0.1.1.dist-info/RECORD
