Metadata-Version: 2.1
Name: ladybug-blender
Version: 0.1.1
Summary: Ladybug plugin for Blender.
Home-page: https://github.com/ladybug-tools/ladybug-blender
Author: Ladybug Tools
Author-email: info@ladybug.tools
License: UNKNOWN
Platform: UNKNOWN
Classifier: Programming Language :: Python :: 3.6
Classifier: Programming Language :: Python :: 3.7
Classifier: Programming Language :: Python :: Implementation :: CPython
Classifier: License :: OSI Approved :: GNU General Public License v3 (GPLv3)
Classifier: Operating System :: OS Independent
